stabiliser_suite/__init__.py
stabiliser_suite/benchmark.py
stabiliser_suite/circuit.py
stabiliser_suite/clifford.py
stabiliser_suite/gate_utils.py
stabiliser_suite/utils.py
stabilisersuite-1.1.11.dist-info/licenses/LICENSE
stabilisersuite-1.1.11.dist-info/METADATA
stabilisersuite-1.1.11.dist-info/WHEEL
stabilisersuite-1.1.11.dist-info/top_level.txt
stabilisersuite-1.1.11.dist-info/RECORD
