Metadata-Version: 2.4
Name: StabiliserSuite
Version: 1.1.11
Summary: Toolbox for Quantum Computer testing.
Author-email: Anton Perepelenko <anton.perepelenko@achaad.eu>
Maintainer-email: Anton Perepelenko <anton.perepelenko@achaad.eu>
License: MIT
Project-URL: repository, https://github.com/Achaad/StabiliserSuite/
Project-URL: Bug Tracker, https://github.com/Achaad/StabiliserSuite/issues
Keywords: quantum computing,nisq,clifford circuits,stabiliser,stabilizer formalism,gate transformation,tableau simulation,quantum benchmarking,qiskit,gate decomposition,python toolbox
Classifier: Development Status :: 4 - Beta
Classifier: License :: OSI Approved :: MIT License
Classifier: Intended Audience :: Science/Research
Classifier: Intended Audience :: Developers
Classifier: Operating System :: OS Independent
Classifier: Natural Language :: English
Classifier: Topic :: Scientific/Engineering :: Physics
Classifier: Topic :: Scientific/Engineering :: Quantum Computing
Classifier: Topic :: Software Development :: Testing
Classifier: Topic :: Software Development :: Libraries :: Python Modules
Classifier: Environment :: Console
Classifier: Programming Language :: Python :: 3
Classifier: Programming Language :: Python :: 3 :: Only
Classifier: Programming Language :: Python :: 3.9
Classifier: Programming Language :: Python :: 3.10
Classifier: Programming Language :: Python :: 3.11
Classifier: Programming Language :: Python :: 3.12
Requires-Python: >=3.12
License-File: LICENSE
Requires-Dist: numpy>=2.2.0
Requires-Dist: termtables>=0.2.0
Requires-Dist: build>=1.2.0
Requires-Dist: qiskit>=1.3.0
Requires-Dist: numba>=0.61.0
Requires-Dist: tqdm>=4.67.0
Provides-Extra: test
Requires-Dist: pytest>=8.3.0; extra == "test"
Dynamic: license-file
